<xml>
<cell role="date"><date when="2020-01-06">M 1-06</date></cell>
<cell role="date"><date when="2020-01-08">W 1-08</date></cell>
<cell role="date"><date when="2020-01-10">F 1-10</date></cell>
<cell role="date"><date when="2020-01-13">M 1-13</date></cell>
<cell role="date"><date when="2020-01-15">W 1-15</date></cell>
<cell role="date"><date when="2020-01-17">F 1-17</date></cell>
<cell role="date"><date when="2020-01-20">M 1-20</date></cell>
<cell role="date"><date when="2020-01-22">W 1-22</date></cell>
<cell role="date"><date when="2020-01-24">F 1-24</date></cell>
<cell role="date"><date when="2020-01-27">M 1-27</date></cell>
<cell role="date"><date when="2020-01-29">W 1-29</date></cell>
<cell role="date"><date when="2020-01-31">F 1-31</date></cell>
<cell role="date"><date when="2020-02-03">M 2-03</date></cell>
<cell role="date"><date when="2020-02-05">W 2-05</date></cell>
<cell role="date"><date when="2020-02-07">F 2-07</date></cell>
<cell role="date"><date when="2020-02-10">M 2-10</date></cell>
<cell role="date"><date when="2020-02-12">W 2-12</date></cell>
<cell role="date"><date when="2020-02-14">F 2-14</date></cell>
<cell role="date"><date when="2020-02-17">M 2-17</date></cell>
<cell role="date"><date when="2020-02-19">W 2-19</date></cell>
<cell role="date"><date when="2020-02-21">F 2-21</date></cell>
<cell role="date"><date when="2020-02-24">M 2-24</date></cell>
<cell role="date"><date when="2020-02-26">W 2-26</date></cell>
<cell role="date"><date when="2020-02-28">F 2-28</date></cell>
<cell role="date"><date when="2020-03-02">M 3-02</date></cell>
<cell role="date"><date when="2020-03-04">W 3-04</date></cell>
<cell role="date"><date when="2020-03-06">F 3-06</date></cell>
<cell role="date"><date when="2020-03-09">M 3-09</date></cell>
<cell role="date"><date when="2020-03-11">W 3-11</date></cell>
<cell role="date"><date when="2020-03-13">F 3-13</date></cell>
<cell role="date"><date when="2020-03-16">M 3-16</date></cell>
<cell role="date"><date when="2020-03-18">W 3-18</date></cell>
<cell role="date"><date when="2020-03-20">F 3-20</date></cell>
<cell role="date"><date when="2020-03-23">M 3-23</date></cell>
<cell role="date"><date when="2020-03-25">W 3-25</date></cell>
<cell role="date"><date when="2020-03-27">F 3-27</date></cell>
<cell role="date"><date when="2020-03-30">M 3-30</date></cell>
<cell role="date"><date when="2020-04-01">W 4-01</date></cell>
<cell role="date"><date when="2020-04-03">F 4-03</date></cell>
<cell role="date"><date when="2020-04-06">M 4-06</date></cell>
<cell role="date"><date when="2020-04-08">W 4-08</date></cell>
<cell role="date"><date when="2020-04-10">F 4-10</date></cell>
<cell role="date"><date when="2020-04-13">M 4-13</date></cell>
<cell role="date"><date when="2020-04-15">W 4-15</date></cell>
<cell role="date"><date when="2020-04-17">F 4-17</date></cell>
</xml>